{
  "id": "cafeteria-sulounge",
  "name": "SU-Lounge",
  "weekStart": "2026-05-18",
  "menus": [
    {
      "date": "2026-05-18",
      "day": "월",
      "meals": {
        "breakfast": [
          "참치김치덮밥",
          "우동국",
          "양배추샐러드",
          "단무지"
        ],
        "lunch": {
          "a_corner": [
            "*한식DAY*",
            "백미밥",
            "옛날도시락반찬",
            "맑은무우채국",
            "실곤약무침",
            "고구마맛탕",
            "깍두기"
          ],
          "b_corner": [
            "프리미엄샐러드",
            "(오늘의메인토핑 : 오이크래미 )",
            "플레인요거트&그래놀라"
          ]
        },
        "dinner": [
          "백미밥",
          "치즈소시지순두부찌개",
          "표고탕수육",
          "어묵콩나물볶음",
          "깍두기"
        ]
      }
    },
    {
      "date": "2026-05-19",
      "day": "화",
      "meals": {
        "breakfast": [
          "소고기필라프",
          "우동국",
          "양배추샐러드",
          "깍두기"
        ],
        "lunch": {
          "a_corner": [
            "*분식DAY*",
            "참치야채비빔밥",
            "가쓰오장국",
            "치킨너겟&소스",
            "단무지",
            "수제청포도에이드"
          ],
          "b_corner": [
            "프리미엄샐러드",
            "(오늘의메인토핑 : 낫또 )",
            "플레인요거트&그래놀라"
          ]
        },
        "dinner": [
          "백미밥",
          "옹심이만두국",
          "매콤닭구이&깻잎무쌈",
          "파절이무침",
          "포기김치"
        ]
      }
    },
    {
      "date": "2026-05-20",
      "day": "수",
      "meals": {
        "breakfast": [
          "장조림버터비빔밥",
          "우동국",
          "양배추샐러드",
          "깍두기"
        ],
        "lunch": {
          "a_corner": [
            "*누들DAY*",
            "마라탕",
            "계란볶음밥",
            "카레춘권",
            "파이향과(오이탕탕이)",
            "단무지",
            "쿨피스(복숭아)"
          ],
          "b_corner": [
            "프리미엄샐러드",
            "(오늘의메인토핑 : 소불고기 )",
            "플레인요거트&그래놀라"
          ]
        },
        "dinner": [
          "매콤떡볶이",
          "어묵국",
          "후리가케밥",
          "만두깐풍기",
          "단무지"
        ]
      }
    },
    {
      "date": "2026-05-21",
      "day": "목",
      "meals": {
        "breakfast": [
          "치킨소시지볶음밥",
          "우동국",
          "양배추샐러드",
          "깍두기"
        ],
        "lunch": {
          "a_corner": [
            "*덮밥DAY*",
            "수제야채텐동",
            "미소된장국",
            "미트볼케찹조림",
            "토마토유자샐러드",
            "락교&초생강",
            "포기김치"
          ],
          "b_corner": [
            "프리미엄샐러드",
            "(오늘의메인토핑 : 치킨텐더 )",
            "플레인요거트&그래놀라"
          ]
        },
        "dinner": [
          "백미밥",
          "소고기버섯샤브국",
          "치킨샐러드",
          "간장계란장",
          "포기김치"
        ]
      }
    },
    {
      "date": "2026-05-22",
      "day": "금",
      "meals": {
        "breakfast": [
          "백미밥",
          "감자수제비",
          "오이지무침",
          "깍두기"
        ],
        "lunch": {
          "a_corner": [
            "*비건DAY*",
            "백미밥",
            "김치두부짜글이",
            "야끼우동",
            "버섯오색볶음",
            "열무물김치"
          ],
          "b_corner": [
            "프리미엄샐러드",
            "(오늘의메인토핑 : 두부버섯구이 )",
            "플레인요거트&그래놀라"
          ]
        },
        "dinner": [
          "운영 없음"
        ]
      }
    }
  ],
  "lastUpdated": "2026-05-23T02:12:16.328268"
}
